itk/_ITKGPUImageFilterBasePython.so
itk/itkGPUCastImageFilterPython.py
itk/itkGPUBoxImageFilterPython.py
itk/itkGPUNeighborhoodOperatorImageFilterPython.py
itk/ITKGPUImageFilterBasePython.py
itk/.libs/libOpenCL-a4ace450.so.1
itk/Configuration/ITKGPUImageFilterBaseConfig.py
itk_gpuimagefilterbase-0.2.0.dist-info/METADATA
itk_gpuimagefilterbase-0.2.0.dist-info/RECORD
itk_gpuimagefilterbase-0.2.0.dist-info/top_level.txt
itk_gpuimagefilterbase-0.2.0.dist-info/WHEEL
